gemmi/gemmi_ext.cpython-311-darwin.so
gemmi/__init__.pyi
gemmi/__init__.py
gemmi/cif.pyi
gemmi/py.typed
gemmi/examples/hello.py
gemmi/examples/to_rdkit.py
gemmi/examples/mtz_i_sigi.py
gemmi/examples/simple_search.py
gemmi/examples/aafreq.py
gemmi/examples/rama_gather.py
gemmi/examples/ccd_subgraph.py
gemmi/examples/matthews.py
gemmi/examples/rama_plot.py
gemmi/examples/mtrix_iso.py
gemmi/examples/maskcheck.py
gemmi/examples/maskdiff.py
gemmi/examples/sub_ccd.py
gemmi/examples/weight.py
gemmi/examples/from_json.py
gemmi/examples/refln-stats.py
gemmi/examples/cif_i_sigi.py
gemmi/examples/map2mtz.py
gemmi/examples/ccd_gi.py
gemmi/examples/patterson_slice.py
gemmi/examples/col_order.py
gemmi/examples/qq-plot.py
gemmi/examples/monomers.py
gemmi/examples/multiproc.py
gemmi/examples/long_geom.py
gemmi/examples/merge_mtz_mmcif.py
gemmi-0.7.0.dist-info/RECORD
gemmi-0.7.0.dist-info/WHEEL
gemmi-0.7.0.dist-info/METADATA
gemmi-0.7.0.dist-info/licenses/LICENSE.txt
