Metadata-Version: 2.1
Name: gemmi
Version: 0.7.0
Summary: library for structural biology
Keywords: structural bioinformatics,structural biology,crystallography,CIF,mmCIF,PDB,CCP4,MTZ
Home-page: https://github.com/project-gemmi/gemmi
Author-Email: Marcin Wojdyr <wojdyr@gmail.com>
License: MPL-2.0
Classifier: Development Status :: 4 - Beta
Classifier: Intended Audience :: Developers
Classifier: Intended Audience :: Science/Research
Classifier: License :: OSI Approved :: Mozilla Public License 2.0 (MPL 2.0)
Classifier: Topic :: Software Development :: Libraries :: Python Modules
Classifier: Topic :: Scientific/Engineering :: Bio-Informatics
Classifier: Topic :: Scientific/Engineering :: Chemistry
Classifier: Programming Language :: C++
Classifier: Programming Language :: Python
Project-URL: Homepage, https://github.com/project-gemmi/gemmi
Project-URL: Repository, https://github.com/project-gemmi/gemmi
Requires-Python: >=3.8
